szkGraph/__init__.py
szkGraph/szkGraph.py
szkgraph-0.0.2.dist-info/METADATA
szkgraph-0.0.2.dist-info/WHEEL
szkgraph-0.0.2.dist-info/licenses/LICENSE
szkgraph-0.0.2.dist-info/RECORD
