Metadata-Version: 2.3
Name: szkGraph
Version: 0.0.2
Summary: An easy graph formatting tool for matplotlib
Project-URL: Homepage, https://github.com/MP931/szkGraph
Project-URL: Issues, https://github.com/MP931/szkGraph/issues
Author-email: Mahiro Sawada <sawada.mahiro@gmail.com>
License-File: LICENSE
Classifier: License :: OSI Approved :: MIT License
Classifier: Operating System :: OS Independent
Classifier: Programming Language :: Python :: 3
Requires-Python: >=3.9
Requires-Dist: matplotlib>=3.8.0
